{"aarakocra": ["Qruf", "Cak", "Claiac", "Uck", "Rihk", "Yucce", "Greras", "Qala", "Oociarc", "Qrullaa"], "aasimar": ["Zevir", "Caulem", "Eiltir", "Moggan", "Brinlil", "Balrim", "Ryvitant", "Alditint", "Mylgivim", "Nyrranem"], "bugbear": ["Bik", "Bruth", "Chrirr", "Ghurdirk", "Thor", "Khark", "Ghuddun", "Khiddir", "Zhorgimkk", "Khozzar"], "centaur": ["Manva Timberdancer", "Kolvame Laurelrest", "Melzrild Stoneblesser", "Thaeld Winterprowl", "Thaes'Zeh Birchmask", "Tellard Stormformer", "Ghem'Vuth Icecleanser", "On'Red Stonegatherer", "Olzut Icewhisperer", "Gwoth Suntrampler"], "changeling": ["Wurx", "Tars", "Yosk", "Bits", "Daets", "Teeks", "Buts", "Beesk", "Juts", "Mikt"], "deep": ["Krithir Spinelgatherer", "Zhainthen Zirconbreaker", "Bregglit Gemhewer", "Kredmurs Steelheart", "Shithrug Spinelcollector", "Kendald Quartzback", "Koti Claylegs", "Schneckteld Pitwatcher", "Grudlul Dusttooth", "Snitrind Copperbreaker"], "deva": ["Viebahr", "Kerihk", "Ennehm", "Mihihr", "Ovah", "Teban", "Narsar", "Neril", "Sochan", "Hohrahk"], "dragonborn": ["Tamran Yorfras", "Kuuponthoc Aliskan", "Myexil Goragrax", "Shempuan Bhazavur", "Dirrhish Nesrakas", "Nemter Tomorn", "Cluanceaxur Nazavur", "Pruthtokid Krivwunax", "Ildrecmaak Brenwarum", "Yomman Dohazar"], "drow": ["Tazaufein Godeviir", "Drizinyon Kenduis", "Szineth Arabmtor", "Szinonim Arkensek", "Quaverin Nyth", "Vlonthan Mizzrith", "Elthym Keteeruil", "Nykantar Mizzral", "Jeggred Duskryn", "Syrdar Baenre"], "duergar": ["Harbek Flamepass", "Urmrum Brokencrag", "Vondrak Trollreach", "Vonkom Wickedfavor", "Brumkom Forgebelch", "Bromdar Brokenhunt", "Bunmyl Proudforce", "Brangrom Flintbeard", "Hurgram Oreslayer", "Rantharn Proudpride"], "dwarf": ["Duldrak Lastshield", "Gralbrek Halfhand", "Thodar Blackshaper", "Bhelnyl Bloodtankard", "Kardur Boulderreach", "Daernom Bodack", "Ebdek Bolbrinak", "Ranbek Grufdur", "Ebnus Merthuhick", "Gulgrun Strolbrar"], "eladrin": ["Uriurian", "Irakris", "Lanwirn", "Narkbin", "Quaxeral", "Iraoros", "Coraster", "Aranvis", "Zorkris", "Lanikul"], "elf": ["Iligeiros Rainflower", "Qiquinal Fallmoon", "Waesxalim Summerseeker", "Heisandoral Eldermoon", "Yindan Ravenfall", "Uridan Galdristrann", "Sardan Lurdethro", "Yelhice Veistanthra", "Beiyarus Yiethront", "Miranelis Drithrecia"], "fairy": ["Sarsandoral", "Miragolor", "Qinmenor", "Radan", "Tewtigirn", "Retanet", "Thistle", "Calico", "Nelly", "Ginko"], "firbolg": ["Waesxidor Gembreath", "Elajeon Moonseeker", "Umedan Elmcloud", "Mortoris Cedargazer", "Beiberos Bluegazer", "Ianpeiros Kenissin", "Wranberos Quundroxesish", "Rowarin Dreneminn", "Miraxalim Fulto", "Normaris Nenescith"], "genasi": ["Torch", "Calcine", "Phoenix", "Sprinkle", "Stream", "Aqua", "Sand", "Soapstone", "Sediment", "Whisk", "Stratosphere", "Azure"], "githyanki": ["V'A'Rolran", "Trokaruc", "Vr'A'Apoth", "Vik'I'C", "Dik'A'C", "'A'Koth", "Len", "Trekaroc", "Xan'I'C", "Kymaruc"], "githzerai": ["Nirdahn", "Sharzth", "Dakiak", "Bralian", "Grokhar", "Fernak", "Muudran", "Khadahn", "Azad", "Unakk"], "gnome": ["Mancryn Quietgrace", "Salpos Thundercord", "Jordon Dapplehold", "Jegim Bellyflight", "Yerug Gobblegrace", "Merybar Silrusirel", "Vormorn Fableseble", "Aripos Hacklatoll", "Yostix Lornodebeg", "Davfan Bekkesomp"], "goblin": ["Idrark", "Rochus", "Vreglalk", "Vrogg", "Sugdelk", "Fatteeth", "Slugflank", "Slugwill", "Greasearm", "Deviant"], "goliath": ["Kazalig Stormaid Agu-Vatake", "Thogath Silentherder Vuma-Thigane", "Thavanihl Mountainbreaker Vathunukane", "Nakon Thunderguard Kolakamune", "Laumith Hornstalker Valu-Nugoni", "Vaugak Lonekiller Anakalukane", "Kazanihl Deerlander Nugalamune", "Kavazak Thundercaller Thulatake", "Geanihl Longchaser Inuligane", "Mauman Deerbreaker Egumutha"], "grung": ["g'Oung'b'Oung", "d'As", "d'As", "n'Dieb", "r'Dehp", "c'Ruhn", "g'Ub'r'Ub", "g'Neen", "c'Dung", "p'Nen"], "half": ["Urthaburk", "Gromidash", "Keludim", "Ogguosk", "Mokisk", "Sorizar", "Sorudur", "Momarsh", "Kurusk", "Trukork"], "halfling": ["Iranad Copperspell", "Elser Freecheeks", "Tevon Stonehill", "Ulfire Eldersun", "Arry Twilightcrest", "Janhorn Smoothbelly", "Elmin Mildleaf", "Cormo Bramblegather", "Marzin Nightvale", "Conmin Barleyberry"], "harengon": ["Jemneh", "Tragde", "Dorro", "Elmelot", "Zonnit", "Druddivot", "Umero", "Aexidor", "Petdan", "Traven"], "hobgoblin": ["Zakrag", "Okurug", "Zonkarz", "Men", "Zokrerz", "Glundon The Hunter", "Olzodec Duel", "Shok Kill", "Kharkal The Butcher", "Vravlen Forge"], "human": ["Misan Bhahli", "Khurdem Shodu", "Graldorn Winterfeather", "Birkark Marshshard", "Evil Rirsk", "Bel Baknog", "Bremen Rageflayer", "Frath Roseforest", "Ridek-Res Benkrenzut", "Zehvoth Nunthekt", "Filvordoc Tuguldago", "Bauldar Zidzuka", "Thuh Kia", "Aw Saing", "Acanraiz Vergildin", "Chiercul Mosqime"], "kalashtar": ["Geliulad", "Golhareth", "Votash", "Tewmelk", "Ganmelk", "Dezil", "Tehirra", "Chonale", "Beshtoth", "Hilodraint"], "kenku": ["Jangler", "Duster", "Clucker", "Plunger", "Goose Hiss", "Dog Wiggle", "Swan Cry", "Kettle Bubble", "Net Cast", "Hammer Clank"], "kobold": ["Hur", "Tugs", "Vorn", "Nex", "Siva", "Tuvlu", "Snilti", "Ugla", "Ruhle", "Ikke"], "leonin": ["Tios Stormhide", "Prorion Silenthold", "Egtu Longfield", "Piknez Grandclaw", "Pagnes Gloommoon", "Zemon Roughdream", "Xeor Fiercerest", "Xematho Grandcaller", "Deknun Sundream", "Gaknomu Smoothweaver"], "lizardfolk": ["Jhesk", "Rerd", "Ortyrth", "Ighex", "Shaghuk", "Bothu", "Trushyx", "Durhtigir", "Oshrithaosh", "Dashecank"], "locathah": ["Thulam", "Heaoun", "Numith", "Vorit", "Kirus", "Thennum", "Dhavin", "Ravul", "Mollil", "Hozal"], "loxodon": ["Ordul", "Dalon", "Elus", "Siborozh", "Olruj", "Brodjunoz", "Tahoj", "Donrum", "Rolezh", "Soov"], "minotaur": ["Hinetred Thunderwalker", "Emra Thunderslash", "Tiala Singleslayer", "Teezara Thunderwarrior", "Tinatris Greatroar", "Drinmanuk Fearlessstep", "Brannarun Steadyleader", "Noerios Wolfslayer", "Codnark Nimbleslayer", "Grafran Valiantslash"], "orc": ["Rukk Brass Wrecker", "Rhull Horror Glaive", "Zhod The Gross", "Bhall Spite Blade", "Lomok The Vicious", "Ozukk The Dark", "Nogvokk The Silent", "Zhogrol Scale Spear", "Lorlod Flame Squisher", "Bhobzul The Mad"], "satyr": ["Feolon", "Nefizian", "Peomenos", "Pantizos", "Zokyppos", "Dimos", "Ykon", "Imatias", "Deoferos", "Fanako"], "shadar": ["Hennon", "Annathok", "Nirrin", "Higan", "Zeran", "Crerran", "Crushathach", "Agan", "Udal", "Tharrin"], "shardmind": ["Lutiru", "Balayara", "Seluyua", "Arsharin", "Sarirashi", "Utshi", "Naranashtu", "Sanaku", "Maraha", "Kubanu"], "shifter": ["River", "Steel", "Grime", "Canyon", "Gorge", "Gorge", "Fang", "Frostbite", "Basil", "Frost"], "simic": ["Sewaulad", "Khulad", "Mezmelk", "Meriulad", "Chanmelk", "Yelpeiros", "Qinmenor", "Pavalur", "Qifaren", "Kelberos"], "tabaxi": ["Afternoon Nap (Nap)", "Tricking Treat (Trick)", "Forgotten Link (Link)", "Strength of Love (Love)", "Windy Shore (Shore)", "Tranquil Bear (Tranquil)", "Half Needle (Half)", "Ancient Aspect (Ancient)", "Light Chalk (Light)", "Silent Sea (Silent)"], "tiefling": ["Reakos", "Xarmos", "Malelius", "Sirlyre", "Rolxus", "Morros", "Garrakas", "Aranthos", "Xarrakir", "Erthor"], "tortle": ["Qannell", "Krinluk", "Dal", "Duonqwu", "Olkoc", "Sardlin", "Plett", "Boqwo", "Ozly", "Xunno"], "triton": ["Kheres Gevugath", "Jhahnas Abonzath", "Jehres Pavorath", "Junvus Nahransath", "Khilnis Nagalmath", "Rumus Zanogath", "Relmes Uvamnath", "Muldus Dhebalnath", "Zenres Rudonath", "Curvus Sohlonsath"], "vedalken": ["Peved", "Arivut", "Movrec", "Bhebon", "Unaroz", "Dhuluniz", "Yavlud", "Otev", "Detlel", "Khoggish"], "warforged": ["Wielder", "Saviour", "Sentinel", "Winker", "Walker", "Climber", "Sentinel", "Wonderer", "Fighter", "Tinkerer"], "wilden": ["Lonnorten", "Fasdarris", "Middarris", "Sansorran", "Mornorten", "Farringun", "Harrunnas", "Karrenmin", "Kettenbar", "Barrundin"], "yuan": ["Sokhia", "Huizsha", "Yusta", "Shehlui", "Thuhlish", "Theszi", "Soalshoazhu", "Yizhoassu", "Zehshishliul", "Ushellias"], "archdevil": ["Taimjurach", "Zeth", "Fenzem", "Etech", "Rispastul", "Roteth", "Ulkulu", "Tulgal", "Zophem", "Onrenim"], "archfey": ["Mimathon", "Rylan", "Ralnoth", "Thiras", "Ninulum", "Milnos", "Kulralath", "Kelneth", "Cyles", "Nilnath"], "beholder": ["Fa", "Aksh", "Khozu", "Irdocs", "Arnicsh", "Vodocs", "Badthrarolks", "Chemlyrsaeks", "Althoka", "Odtruzeqea"], "bullywug": ["Zpaff", "Spoux", "Gap", "Trundux", "Mux", "Droltid", "Grandluth", "Blirbluf", "Niglux", "Zpoglof"], "demon": ["Olvasahe", "Dostisux", "Dwarco", "Groblilcier", "Gipurtir", "Yerlgo", "Sargun", "Kastes", "Karmur", "Pamussoghei"], "black": ["Azagylgrurg", "Conglissal", "Vostilomithurg", "Thralalloth", "Nenstyth", "Garyrgof", "Halfhunter", "The Ill Tempered", "The Bitter", "The Careful"], "blue": ["Ashintes", "Memeszor", "Tolmithrok", "Vurtrivarin", "Chunthrakredun", "Skanthruugovuvar", "The Master", "Duskbreath", "The Rich", "The Fierce"], "brass": ["Kindathlirol", "Kimdretham", "Gervethlar", "Thirdrathlan", "Irlathi", "Soluvin", "The Brilliant Mind", "Swifteye", "Keenwatcher", "Lightglide"], "bronze": ["Sressivoth", "Somrerh", "Vomshuth", "Zuhdriakid", "Fryryos", "Mulmusur", "The Maniac", "The Bright", "Moongrip", "Bigbrow"], "copper": ["Donadaezma", "Mitazmad", "Ravumathlod", "Zathuzrad", "Nathono", "Nirhurernith", "The Damned", "The Calm", "Flamereader", "The Behemoth"], "gold": ["Drareslas", "Gaeramethodar", "Gadrith", "Pralgix", "Tolgirk", "Alnolanond", "Masterteeth", "The Innocent", "The Adored", "The Vengeful"], "green": ["Uvoxoth", "Drerthor", "Voshtithallos", "Chimex", "Jotchredrir", "Cheshilash", "The Watcher", "The Anguished", "The Wretched", "The Lost Mind"], "platinum": ["Ahim", "Hodrulas", "Talninar", "Ruruvem", "Ondadun", "Odem", "The Forsaken", "The Wicked", "The Judge", "The Beautiful"], "red": ["Dremverh", "Shamdraurten", "Kimdrangriath", "Yphaelik", "Rhirramonic", "Thilcandoth", "Powerwing", "Palebeast", "Terrorgrip", "The Bold"], "silver": ["Arlas", "Clilalaijiot", "Zilallus", "Akkorkuteq", "Clizhen", "Delaillejetam", "The Adored", "The Innocent", "Glowcutter", "The Delirious"], "white": ["Methuxamithar", "Crithunfrax", "Yklanfrar", "Glissurrenhar", "Kixis", "Glyrbex", "Swiftfangs", "Burningstriker", "The Anxious", "The Enchanting"], "genie": ["Mutaal", "Labaar al-Bakoos", "Tufaimaan", "Kamih", "Bilaas al-Yooseed", "Zaamahim al-Hibbi", "Yoonallah", "Nizid", "Nadaas", "Murshaal"], "giant": ["Throllem", "Grorkart", "Soksentem", "Manzart", "Grulnurt", "Mumnan", "Aannes", "Aannos", "Thaztur", "Gugnart"], "gnoll": ["Ared Of The Menacing Miscreants", "Uyuk Of The Hollow Freaks", "Erbalk Of The Vicious Varmints", "Olthalk Of The Decayed Bruisers", "Olad Of The Wicked Vandals", "Ammem Of The Decayed Ferals", "Udnekh Of The Meddling Exterminators", "Udrug Of The Bribing Heralds", "Idak Of The Wicked Battlers", "Elob Of The Hollow Vagabonds"], "hag": ["Old Deanna Marblemingle", "Stumbling Jackie Websister", "Depraved Wendy Verminbody", "Nutty Lila Knuckleshuffler", "Wrinkling Lottie Titchbones", "Bony Billie Blindcobble", "Disfigured Ina Frogsinger", "Bumbling Lynda Mudhand", "Skinny Maryann Scalegoggle", "Acrid Agnes Rubblebiter"], "mind": ["Cult", "Zek", "Odal", "Zabim", "Qezossk", "Rusgult", "Ellibualt", "Zunkemalt", "Vuosdurul", "Thesibonu"], "myconid": ["Yblopliop", "Leeldis", "Rashobrior", "Foogil", "Yildeb", "Hyser", "Edolob", "Hadil", "Ysterbub", "Psabap"], "ogre": ["Rarg Darkstrength", "Yug Casksnarl", "Zundort Bloodsplinter", "Gramrag Wildshoulder", "Nedak Granitehole", "Krazzean Battlemight", "Yal Roughstrength", "Vul Twilightsplinter", "Tag Goldslayer", "Breth Darkwatcher"], "pixie": ["Purple", "Shimmersand", "Greenbutter", "Willow", "Dazzleclover", "Canyon", "Minerva", "Fantasia", "Cranberry", "Dey"], "treant": ["Balvalur", "Qixidor", "Fenna", "Qinvyre", "Genrora", "Peachsnarl", "Pygmyjuniper", "Treetwig", "Peachflesh", "Cherrybrow"], "troll": ["Brezik", "Pin", "Chozkak", "Pezkek", "Tug", "Kuk", "Kezkig", "Sret", "Chek", "Tedkar"], "troglodyte": ["Krekk", "Zert", "Zest", "Plusk", "Thid", "Thiz'Kol", "Halk", "Grud", "Gur", "Hos'Tall"]}